infrared_virsh-3.0.0.dist-info/DESCRIPTION.rst
infrared_virsh-3.0.0.dist-info/METADATA
infrared_virsh-3.0.0.dist-info/RECORD
infrared_virsh-3.0.0.dist-info/WHEEL
infrared_virsh-3.0.0.dist-info/entry_points.txt
infrared_virsh-3.0.0.dist-info/metadata.json
infrared_virsh-3.0.0.dist-info/pbr.json
infrared_virsh-3.0.0.dist-info/top_level.txt
virsh/__init__.py
virsh/cleanup.yml
virsh/collect-ansible-facts.yml
virsh/main.yml
virsh/plugin.spec
virsh/post.yml
virsh/pre.yml
virsh/prepare_hypervisor.yml
virsh/provision.yml
virsh/provision_networks.yml
virsh/provision_user.yml
virsh/provision_vms.yml
virsh/validate_hypervisor.yml
virsh/defaults/topology/network/1_net.yml
virsh/defaults/topology/network/3_nets.yml
virsh/defaults/topology/network/3_nets_1_bridge.yml
virsh/defaults/topology/network/5_nets.yml
virsh/defaults/topology/network/split_nets.yml
virsh/defaults/topology/nodes/aio.yml
virsh/defaults/topology/nodes/ceph.yml
virsh/defaults/topology/nodes/cfme.yml
virsh/defaults/topology/nodes/compute.yml
virsh/defaults/topology/nodes/contnet.yml
virsh/defaults/topology/nodes/controller.yml
virsh/defaults/topology/nodes/database.yml
virsh/defaults/topology/nodes/diskless.yml
virsh/defaults/topology/nodes/freeipa.yml
virsh/defaults/topology/nodes/heat.yml
virsh/defaults/topology/nodes/ironic.yml
virsh/defaults/topology/nodes/loadbalancer.yml
virsh/defaults/topology/nodes/messaging.yml
virsh/defaults/topology/nodes/monitor.yml
virsh/defaults/topology/nodes/networker.yml
virsh/defaults/topology/nodes/novacontrol.yml
virsh/defaults/topology/nodes/odl.yml
virsh/defaults/topology/nodes/openshift-master.yml
virsh/defaults/topology/nodes/openshift-worker.yml
virsh/defaults/topology/nodes/opstools.yml
virsh/defaults/topology/nodes/osdcompute.yml
virsh/defaults/topology/nodes/radosgw.yml
virsh/defaults/topology/nodes/serviceapi.yml
virsh/defaults/topology/nodes/swift.yml
virsh/defaults/topology/nodes/telemetry.yml
virsh/defaults/topology/nodes/tester.yml
virsh/defaults/topology/nodes/tripleo.yml
virsh/defaults/topology/nodes/undercloud.yml
virsh/filter_plugins/filesize.py
virsh/tasks/bridged_network.yml
virsh/tasks/calc_needed_memory.yml
virsh/tasks/cleanup.yml
virsh/tasks/download_images.yml
virsh/tasks/enable_virtualization.yml
virsh/tasks/netip_natted.yml
