Metadata-Version: 2.0
Name: infrared-virsh
Version: 3.0.0
Summary: virsh plugin for InfraRed
Home-page: https://gitlab.cee.redhat.com/ovorobio/infrared-virsh/
Author: Red Hat OpenStack Infrastructure Team
Author-email: rhos-infrared-dev@redhat.com
License: UNKNOWN
Platform: UNKNOWN
Classifier: License :: OSI Approved :: GNU General Public License v3 or later (GPLv3+)
Classifier: Development Status :: 5 - Production/Stable
Classifier: Intended Audience :: Developers
Classifier: Intended Audience :: System Administrators
Classifier: Intended Audience :: Information Technology
Classifier: Topic :: Software Development :: Testing
Classifier: Topic :: Utilities
